fullwave/__init__.py
fullwave/grid.py
fullwave/medium.py
fullwave/sensor.py
fullwave/source.py
fullwave/transducer.py
fullwave/beamformer/beamformer.py
fullwave/beamformer/exp_beamformer.py
fullwave/constants/__init__.py
fullwave/constants/material_properties.py
fullwave/medium_builder/__init__.py
fullwave/medium_builder/domain.py
fullwave/medium_builder/medium_builder.py
fullwave/medium_builder/presets/__init__.py
fullwave/medium_builder/presets/domain_abdominal_wall.py
fullwave/medium_builder/presets/domain_background.py
fullwave/medium_builder/presets/domain_scatterer.py
fullwave/medium_builder/presets/domain_simple.py
fullwave/medium_builder/presets/domain_water_gel.py
fullwave/medium_builder/presets/data/.keep
fullwave/medium_builder/presets/data/abdominal_wall/i2365f_etfw1.mat
fullwave/solver/__init__.py
fullwave/solver/cuda_utils.py
fullwave/solver/input_file_writer.py
fullwave/solver/launcher.py
fullwave/solver/pml_builder.py
fullwave/solver/solver.py
fullwave/solver/utils.py
fullwave/solver/bins/database/relaxation_params_database_num_relax=2_20260113_0957.mat
fullwave/solver/bins/exponential_attenuation/gpu/2d/fullwave2_2d_exponential_attenuation_gpu_sm_100_cuda129
fullwave/solver/bins/exponential_attenuation/gpu/2d/fullwave2_2d_exponential_attenuation_gpu_sm_101_cuda129
fullwave/solver/bins/exponential_attenuation/gpu/2d/fullwave2_2d_exponential_attenuation_gpu_sm_120_cuda129
fullwave/solver/bins/exponential_attenuation/gpu/2d/fullwave2_2d_exponential_attenuation_gpu_sm_61_cuda118
fullwave/solver/bins/exponential_attenuation/gpu/2d/fullwave2_2d_exponential_attenuation_gpu_sm_61_cuda124
fullwave/solver/bins/exponential_attenuation/gpu/2d/fullwave2_2d_exponential_attenuation_gpu_sm_61_cuda126
fullwave/solver/bins/exponential_attenuation/gpu/2d/fullwave2_2d_exponential_attenuation_gpu_sm_61_cuda129
fullwave/solver/bins/exponential_attenuation/gpu/2d/fullwave2_2d_exponential_attenuation_gpu_sm_70_cuda118
fullwave25-1.1.0.dist-info/METADATA
fullwave25-1.1.0.dist-info/WHEEL
fullwave25-1.1.0.dist-info/licenses/LICENSE
fullwave25-1.1.0.dist-info/RECORD
