Metadata-Version: 2.4
Name: fullwave25
Version: 1.1.0
Summary: Fullwave 2.5: Ultrasound wave propagation simulation with heterogeneous power law attenuation modelling capabilities
Author: Masashi Sode, Gianmarco Pinton
Maintainer: Masashi Sode
License-File: LICENSE
Keywords: fdtd,finite-difference,simulation,ultrasound
Classifier: Intended Audience :: Developers
Classifier: Programming Language :: Python :: 3
Classifier: Programming Language :: Python :: 3.10
Classifier: Programming Language :: Python :: 3.11
Classifier: Programming Language :: Python :: 3.12
Classifier: Topic :: Scientific/Engineering :: Physics
Requires-Python: >=3.10
Requires-Dist: matplotlib>=3.10.7
Requires-Dist: numpy>=2.0.0
Requires-Dist: opencv-python-headless>=4.12.0.88
Requires-Dist: scipy>=1.13.1
Requires-Dist: tomli>=2.3.0
Requires-Dist: tqdm>=4.67.1
Provides-Extra: dev
Requires-Dist: pre-commit==4.1.0; extra == 'dev'
Requires-Dist: pytest>=8.3.5; extra == 'dev'
Requires-Dist: ruff>=0.12.9; extra == 'dev'
Provides-Extra: examples
Requires-Dist: ipykernel>=6.28.0; extra == 'examples'
Requires-Dist: jupyter>=1.0.0; extra == 'examples'
Provides-Extra: test
Requires-Dist: pytest; extra == 'test'
Requires-Dist: tomli>=2.3.0; extra == 'test'
